crunchie/main.py
crunchie-205.0.0.dist-info/METADATA
crunchie-205.0.0.dist-info/WHEEL
crunchie-205.0.0.dist-info/top_level.txt
crunchie-205.0.0.dist-info/RECORD
