Metadata-Version: 2.1
Name: crunchie
Version: 205.0.0
Summary: Package that does absolutely nothing 
Home-page: UNKNOWN
Author: daneee
Author-email: daneee@example.com
License: MIT
Platform: UNKNOWN
